MANIFEST.in
README.rst
RELEASE-VERSION
setup.py
version.py
src/streamcorpus/__init__.py
src/streamcorpus/_cbor_chunk.py
src/streamcorpus/_chunk.py
src/streamcorpus/chunk_roller.py
src/streamcorpus/constants.py
src/streamcorpus/constants_v0_1_0.py
src/streamcorpus/constants_v0_2_0.py
src/streamcorpus/dump.py
src/streamcorpus/package_globals.py
src/streamcorpus/test_cbor_chunk.py
src/streamcorpus/test_chunk.py
src/streamcorpus/test_chunk_roller.py
src/streamcorpus/test_dump.py
src/streamcorpus/test_entity_type.py
src/streamcorpus/test_init.py
src/streamcorpus/test_md5.py
src/streamcorpus/test_streamcorpus.py
src/streamcorpus/test_throughput_speed.py
src/streamcorpus/test_xpath.py
src/streamcorpus/ttypes.py
src/streamcorpus/ttypes_v0_1_0.py
src/streamcorpus/ttypes_v0_2_0.py
src/streamcorpus/xpath.py
src/streamcorpus.egg-info/PKG-INFO
src/streamcorpus.egg-info/SOURCES.txt
src/streamcorpus.egg-info/dependency_links.txt
src/streamcorpus.egg-info/entry_points.txt
src/streamcorpus.egg-info/requires.txt
src/streamcorpus.egg-info/top_level.txt