Metadata-Version: 1.1
Name: streamcorpus
Version: 0.3.54
Summary: Tools for organizing a collections of text for entity-centric stream processing.
Home-page: http://github.com/trec-kba/streamcorpus
Author: Diffeo, Inc.
Author-email: support@diffeo.com
License: MIT/X11 license http://opensource.org/licenses/MIT
Platform: UNKNOWN
Classifier: Development Status :: 3 - Alpha
Classifier: Topic :: Utilities
Classifier: License :: OSI Approved :: MIT License
